{
  "presetFields": [
    {
      "name": "Date",
      "options": {
        "dateFormat": "YYYY-MM-DD",
        "defaultInsertAsLink": "false"
      },
      "id": "1",
      "type": "Date",
      "command": {
        "id": "insert__presetField__Date",
        "icon": "calendar",
        "label": "Insert Date field"
      }
    },
    {
      "name": "Tags",
      "options": {
        "valuesList": {},
        "sourceType": "ValuesFromDVQuery",
        "valuesListNotePath": "",
        "valuesFromDVQuery": "dv.pages().file.tags.map(s => s.slice(1)).distinct()"
      },
      "id": "2",
      "type": "Multi",
      "command": {
        "id": "insert__presetField__Tags",
        "icon": "tags",
        "label": "Insert Tags field"
      }
    }
  ],
  "fileClassQueries": [],
  "displayFieldsInContextMenu": true,
  "globallyIgnoredFields": [],
  "classFilesPath": null,
  "isAutosuggestEnabled": true,
  "fileClassAlias": "fileClass",
  "settingsVersion": 3,
  "firstDayOfWeek": 1,
  "enableLinks": true,
  "enableTabHeader": true,
  "enableEditor": true,
  "enableBacklinks": true,
  "enableStarred": true,
  "enableFileExplorer": true,
  "enableSearch": true,
  "buttonIcon": "clipboard-list",
  "tableViewMaxRecords": 100,
  "frontmatterListDisplay": "asList"
}